{
    "id": "AutryMedia.csv",
    "name": "AutryMedia.csv",
    "description": null,
    "sourceColumns": [
        {
            "id": "HN13",
            "hNodeId": "HN13",
            "columnName": "AutryObjectURL"
        },
        {
            "id": "HN1349",
            "hNodeId": "HN1349",
            "columnName": "ImageURI"
        },
        {
            "id": "HN722",
            "hNodeId": "HN722",
            "columnName": "ObjectURI"
        },
        {
            "id": "HN1245",
            "hNodeId": "HN1245",
            "columnName": "CreditURI"
        },
        {
            "id": "HN1139",
            "hNodeId": "HN1139",
            "columnName": "AutryObjectURLCopy"
        },
        {
            "id": "HN12",
            "hNodeId": "HN12",
            "columnName": "CreditLine"
        }
    ],
    "mappingToSourceColumns": [
        {
            "id": "HN13",
            "sourceColumnId": "HN13"
        },
        {
            "id": "HN1349",
            "sourceColumnId": "HN1349"
        },
        {
            "id": "HN722",
            "sourceColumnId": "HN722"
        },
        {
            "id": "HN1245",
            "sourceColumnId": "HN1245"
        },
        {
            "id": "HN1139",
            "sourceColumnId": "HN1139"
        },
        {
            "id": "HN12",
            "sourceColumnId": "HN12"
        }
    ],
    "graph": {
        "nodes": [
            {
                "id": "http://www.cidoc-crm.org/cidoc-crm/E22_Man-Made_Object1",
                "label": {
                    "uri": "http://www.cidoc-crm.org/cidoc-crm/E22_Man-Made_Object",
                    "rdfsLabel": null
                },
                "type": "InternalNode",
                "modelIds": null
            },
            {
                "id": "http://www.cidoc-crm.org/cidoc-crm/E38_Image1",
                "label": {
                    "uri": "http://www.cidoc-crm.org/cidoc-crm/E38_Image",
                    "rdfsLabel": null
                },
                "type": "InternalNode",
                "modelIds": null
            },
            {
                "id": "http://xmlns.com/foaf/0.1/Document1",
                "label": {
                    "uri": "http://xmlns.com/foaf/0.1/Document",
                    "rdfsLabel": null
                },
                "type": "InternalNode",
                "modelIds": null
            },
            {
                "id": "http://www.cidoc-crm.org/cidoc-crm/E33_Linguistic_Object1",
                "label": {
                    "uri": "http://www.cidoc-crm.org/cidoc-crm/E33_Linguistic_Object",
                    "rdfsLabel": null
                },
                "type": "InternalNode",
                "modelIds": null
            },
            {
                "id": "HN13",
                "label": {
                    "uri": "HN13",
                    "rdfsLabel": null
                },
                "type": "ColumnNode",
                "hNodeId": "HN13",
                "columnName": "AutryObjectURL",
                "rdfLiteralType": null,
                "language": "",
                "userSemanticTypes": [
                    {
                        "hNodeId": "HN13",
                        "domain": {
                            "uri": "http://xmlns.com/foaf/0.1/Document",
                            "rdfsLabel": null
                        },
                        "type": {
                            "uri": "http://isi.edu/integration/karma/dev#classLink",
                            "rdfsLabel": null
                        },
                        "origin": "User",
                        "confidenceScore": 1.0
                    },
                    {
                        "hNodeId": "HN13",
                        "domain": {
                            "uri": "http://xmlns.com/foaf/0.1/Document",
                            "rdfsLabel": null
                        },
                        "type": {
                            "uri": "http://isi.edu/integration/karma/dev#classLink",
                            "rdfsLabel": null
                        },
                        "origin": "User",
                        "confidenceScore": 1.0
                    }
                ],
                "learnedSemanticTypes": null,
                "modelIds": null
            },
            {
                "id": "HN1349",
                "label": {
                    "uri": "HN1349",
                    "rdfsLabel": null
                },
                "type": "ColumnNode",
                "hNodeId": "HN1349",
                "columnName": "ImageURI",
                "rdfLiteralType": null,
                "language": "",
                "userSemanticTypes": [
                    {
                        "hNodeId": "HN1349",
                        "domain": {
                            "uri": "http://www.cidoc-crm.org/cidoc-crm/E38_Image",
                            "rdfsLabel": null
                        },
                        "type": {
                            "uri": "http://isi.edu/integration/karma/dev#classLink",
                            "rdfsLabel": null
                        },
                        "origin": "User",
                        "confidenceScore": 1.0
                    },
                    {
                        "hNodeId": "HN1349",
                        "domain": {
                            "uri": "http://www.cidoc-crm.org/cidoc-crm/E38_Image",
                            "rdfsLabel": null
                        },
                        "type": {
                            "uri": "http://isi.edu/integration/karma/dev#classLink",
                            "rdfsLabel": null
                        },
                        "origin": "User",
                        "confidenceScore": 1.0
                    }
                ],
                "learnedSemanticTypes": null,
                "modelIds": null
            },
            {
                "id": "HN722",
                "label": {
                    "uri": "HN722",
                    "rdfsLabel": null
                },
                "type": "ColumnNode",
                "hNodeId": "HN722",
                "columnName": "ObjectURI",
                "rdfLiteralType": null,
                "language": "",
                "userSemanticTypes": [
                    {
                        "hNodeId": "HN722",
                        "domain": {
                            "uri": "http://www.cidoc-crm.org/cidoc-crm/E22_Man-Made_Object",
                            "rdfsLabel": null
                        },
                        "type": {
                            "uri": "http://isi.edu/integration/karma/dev#classLink",
                            "rdfsLabel": null
                        },
                        "origin": "User",
                        "confidenceScore": 1.0
                    },
                    {
                        "hNodeId": "HN722",
                        "domain": {
                            "uri": "http://www.cidoc-crm.org/cidoc-crm/E22_Man-Made_Object",
                            "rdfsLabel": null
                        },
                        "type": {
                            "uri": "http://isi.edu/integration/karma/dev#classLink",
                            "rdfsLabel": null
                        },
                        "origin": "User",
                        "confidenceScore": 1.0
                    }
                ],
                "learnedSemanticTypes": null,
                "modelIds": null
            },
            {
                "id": "HN1245",
                "label": {
                    "uri": "HN1245",
                    "rdfsLabel": null
                },
                "type": "ColumnNode",
                "hNodeId": "HN1245",
                "columnName": "CreditURI",
                "rdfLiteralType": null,
                "language": "",
                "userSemanticTypes": [
                    {
                        "hNodeId": "HN1245",
                        "domain": {
                            "uri": "http://www.cidoc-crm.org/cidoc-crm/E33_Linguistic_Object",
                            "rdfsLabel": null
                        },
                        "type": {
                            "uri": "http://isi.edu/integration/karma/dev#classLink",
                            "rdfsLabel": null
                        },
                        "origin": "User",
                        "confidenceScore": 1.0
                    },
                    {
                        "hNodeId": "HN1245",
                        "domain": {
                            "uri": "http://www.cidoc-crm.org/cidoc-crm/E33_Linguistic_Object",
                            "rdfsLabel": null
                        },
                        "type": {
                            "uri": "http://isi.edu/integration/karma/dev#classLink",
                            "rdfsLabel": null
                        },
                        "origin": "User",
                        "confidenceScore": 1.0
                    }
                ],
                "learnedSemanticTypes": null,
                "modelIds": null
            },
            {
                "id": "HN1139",
                "label": {
                    "uri": "HN1139",
                    "rdfsLabel": null
                },
                "type": "ColumnNode",
                "hNodeId": "HN1139",
                "columnName": "AutryObjectURLCopy",
                "rdfLiteralType": null,
                "language": "",
                "userSemanticTypes": [
                    {
                        "hNodeId": "HN1139",
                        "domain": {
                            "uri": "http://xmlns.com/foaf/0.1/Document",
                            "rdfsLabel": null
                        },
                        "type": {
                            "uri": "http://www.w3.org/2000/01/rdf-schema#label",
                            "rdfsLabel": null
                        },
                        "origin": "User",
                        "confidenceScore": 1.0
                    },
                    {
                        "hNodeId": "HN1139",
                        "domain": {
                            "uri": "http://xmlns.com/foaf/0.1/Document",
                            "rdfsLabel": null
                        },
                        "type": {
                            "uri": "http://www.w3.org/2000/01/rdf-schema#label",
                            "rdfsLabel": null
                        },
                        "origin": "User",
                        "confidenceScore": 1.0
                    }
                ],
                "learnedSemanticTypes": null,
                "modelIds": null
            },
            {
                "id": "HN12",
                "label": {
                    "uri": "HN12",
                    "rdfsLabel": null
                },
                "type": "ColumnNode",
                "hNodeId": "HN12",
                "columnName": "CreditLine",
                "rdfLiteralType": null,
                "language": "",
                "userSemanticTypes": [
                    {
                        "hNodeId": "HN12",
                        "domain": {
                            "uri": "http://www.cidoc-crm.org/cidoc-crm/E33_Linguistic_Object",
                            "rdfsLabel": null
                        },
                        "type": {
                            "uri": "http://www.w3.org/1999/02/22-rdf-syntax-ns#value",
                            "rdfsLabel": null
                        },
                        "origin": "User",
                        "confidenceScore": 1.0
                    },
                    {
                        "hNodeId": "HN12",
                        "domain": {
                            "uri": "http://www.cidoc-crm.org/cidoc-crm/E33_Linguistic_Object",
                            "rdfsLabel": null
                        },
                        "type": {
                            "uri": "http://www.w3.org/1999/02/22-rdf-syntax-ns#value",
                            "rdfsLabel": null
                        },
                        "origin": "User",
                        "confidenceScore": 1.0
                    }
                ],
                "learnedSemanticTypes": null,
                "modelIds": null
            },
            {
                "id": "http://vocab.getty.edu/aat/3000266871",
                "label": {
                    "uri": "",
                    "rdfsLabel": null
                },
                "type": "LiteralNode",
                "value": "http://vocab.getty.edu/aat/300026687",
                "datatype": {
                    "uri": "",
                    "rdfsLabel": null
                },
                "language": "",
                "isUri": "true",
                "modelIds": null
            }
        ],
        "links": [
            {
                "id": "http://www.cidoc-crm.org/cidoc-crm/E22_Man-Made_Object1---http://www.cidoc-crm.org/cidoc-crm/P138i_has_representation---http://www.cidoc-crm.org/cidoc-crm/E38_Image1",
                "weight": 0.009999999776482582,
                "type": "ObjectPropertyLink",
                "label": {
                    "uri": "http://www.cidoc-crm.org/cidoc-crm/P138i_has_representation",
                    "rdfsLabel": null
                },
                "objectPropertyType": "Indirect",
                "status": "ForcedByUser",
                "keyInfo": "None",
                "modelIds": null
            },
            {
                "id": "http://www.cidoc-crm.org/cidoc-crm/E22_Man-Made_Object1---http://xmlns.com/foaf/0.1/homepage---http://xmlns.com/foaf/0.1/Document1",
                "weight": 0.009999999776482582,
                "type": "ObjectPropertyLink",
                "label": {
                    "uri": "http://xmlns.com/foaf/0.1/homepage",
                    "rdfsLabel": null
                },
                "objectPropertyType": "WithOnlyRange",
                "status": "ForcedByUser",
                "keyInfo": "None",
                "modelIds": null
            },
            {
                "id": "http://www.cidoc-crm.org/cidoc-crm/E38_Image1---http://www.cidoc-crm.org/cidoc-crm/P67i_is_referred_to_by---http://www.cidoc-crm.org/cidoc-crm/E33_Linguistic_Object1",
                "weight": 0.009999999776482582,
                "type": "ObjectPropertyLink",
                "label": {
                    "uri": "http://www.cidoc-crm.org/cidoc-crm/P67i_is_referred_to_by",
                    "rdfsLabel": null
                },
                "objectPropertyType": "Indirect",
                "status": "ForcedByUser",
                "keyInfo": "None",
                "modelIds": null
            },
            {
                "id": "http://xmlns.com/foaf/0.1/Document1---http://isi.edu/integration/karma/dev#classLink---HN13",
                "weight": 0.01,
                "type": "ClassInstanceLink",
                "label": {
                    "uri": "http://isi.edu/integration/karma/dev#classLink",
                    "rdfsLabel": null
                },
                "status": "ForcedByUser",
                "keyInfo": "UriOfInstance",
                "modelIds": null
            },
            {
                "id": "http://www.cidoc-crm.org/cidoc-crm/E38_Image1---http://isi.edu/integration/karma/dev#classLink---HN1349",
                "weight": 0.01,
                "type": "ClassInstanceLink",
                "label": {
                    "uri": "http://isi.edu/integration/karma/dev#classLink",
                    "rdfsLabel": null
                },
                "status": "ForcedByUser",
                "keyInfo": "UriOfInstance",
                "modelIds": null
            },
            {
                "id": "http://www.cidoc-crm.org/cidoc-crm/E22_Man-Made_Object1---http://isi.edu/integration/karma/dev#classLink---HN722",
                "weight": 0.01,
                "type": "ClassInstanceLink",
                "label": {
                    "uri": "http://isi.edu/integration/karma/dev#classLink",
                    "rdfsLabel": null
                },
                "status": "ForcedByUser",
                "keyInfo": "UriOfInstance",
                "modelIds": null
            },
            {
                "id": "http://www.cidoc-crm.org/cidoc-crm/E33_Linguistic_Object1---http://isi.edu/integration/karma/dev#classLink---HN1245",
                "weight": 0.01,
                "type": "ClassInstanceLink",
                "label": {
                    "uri": "http://isi.edu/integration/karma/dev#classLink",
                    "rdfsLabel": null
                },
                "status": "ForcedByUser",
                "keyInfo": "UriOfInstance",
                "modelIds": null
            },
            {
                "id": "http://xmlns.com/foaf/0.1/Document1---http://www.w3.org/2000/01/rdf-schema#label---HN1139",
                "weight": 0.01,
                "type": "DataPropertyLink",
                "label": {
                    "uri": "http://www.w3.org/2000/01/rdf-schema#label",
                    "rdfsLabel": null
                },
                "status": "ForcedByUser",
                "keyInfo": "None",
                "modelIds": null
            },
            {
                "id": "http://www.cidoc-crm.org/cidoc-crm/E33_Linguistic_Object1---http://www.w3.org/1999/02/22-rdf-syntax-ns#value---HN12",
                "weight": 0.01,
                "type": "DataPropertyLink",
                "label": {
                    "uri": "http://www.w3.org/1999/02/22-rdf-syntax-ns#value",
                    "rdfsLabel": null
                },
                "status": "ForcedByUser",
                "keyInfo": "None",
                "modelIds": null
            },
            {
                "id": "http://www.cidoc-crm.org/cidoc-crm/E33_Linguistic_Object1---http://www.cidoc-crm.org/cidoc-crm/P2_has_type---http://vocab.getty.edu/aat/3000266871",
                "weight": 0.01,
                "type": "ObjectPropertyLink",
                "label": {
                    "uri": "http://www.cidoc-crm.org/cidoc-crm/P2_has_type",
                    "rdfsLabel": "has type"
                },
                "objectPropertyType": "None",
                "status": "ForcedByUser",
                "keyInfo": "None",
                "modelIds": null
            }
        ]
    }
}